README.md
setup.cfg
setup.py
rupo/__init__.py
rupo/api.py
rupo/settings.py
rupo/test_api.py
rupo.egg-info/PKG-INFO
rupo.egg-info/SOURCES.txt
rupo.egg-info/dependency_links.txt
rupo.egg-info/requires.txt
rupo.egg-info/top_level.txt
rupo/data/hyphen-tokens.txt
rupo/data/examples/markup.json
rupo/data/examples/markup.xml
rupo/data/examples/morph_markup.txt
rupo/data/examples/text.txt
rupo/data/examples/text.xml
rupo/dict/__init__.py
rupo/dict/cmu.py
rupo/dict/wiki.py
rupo/dict/zaliznyak.py
rupo/files/__init__.py
rupo/files/reader.py
rupo/files/test_reader.py
rupo/files/test_writer.py
rupo/files/writer.py
rupo/generate/__init__.py
rupo/generate/generator.py
rupo/generate/transforms.py
rupo/main/__init__.py
rupo/main/markup.py
rupo/main/morph.py
rupo/main/test_markup.py
rupo/main/test_tokenizer.py
rupo/main/test_vocabulary.py
rupo/main/tokenizer.py
rupo/main/vocabulary.py
rupo/metre/__init__.py
rupo/metre/metre_classifier.py
rupo/metre/pattern_analyzer.py
rupo/metre/test_metre_classifier.py
rupo/metre/test_pattern_analyzer.py
rupo/rhymes/__init__.py
rupo/rhymes/rhymes.py
rupo/rhymes/test_rhymes.py
rupo/stress/__init__.py
rupo/stress/dict.py
rupo/stress/predictor.py
rupo/stress/test_dict.py
rupo/stress/test_predictor.py
rupo/stress/word.py
rupo/util/__init__.py
rupo/util/data.py
rupo/util/mixins.py
rupo/util/preprocess.py
rupo/util/timeit.py
rupo/util/tqdm_open.py