Metadata-Version: 1.1
Name: rupo
Version: 0.2.8
Summary: RuPo: library for russian poetry analysis and generation
Home-page: https://github.com/IlyaGusev/rupo
Author: Ilya Gusev
Author-email: phoenixilya@gmail.com
License: UNKNOWN
Download-URL: https://github.com/IlyaGusev/rupo/archive/0.2.8.tar.gz
Keywords: poetry,nlp,russian
Platform: UNKNOWN
Classifier: Development Status :: 4 - Beta
Classifier: Intended Audience :: Developers
Classifier: Topic :: Text Processing :: Linguistic
Classifier: License :: OSI Approved :: Apache Software License
Classifier: Natural Language :: Russian
Classifier: Programming Language :: Python :: 3.5
Classifier: Programming Language :: Python :: 3.5
Classifier: Programming Language :: Python :: 3.6
